<?xml version="1.0" encoding="UTF-8" standalone="yes"?>
<events>
    <event>
        <aggregateIdentifier>NL.IMKAD.TIAStuk.900</aggregateIdentifier>
        <sequenceNumber>0</sequenceNumber>
        <type>TIAStuk</type>
        <identifier>e04123d0-bd56-4c7a-bf06-e9a7ce23997e</identifier>
        <metaData>&lt;?xml version="1.0" encoding="UTF-8" standalone="yes"?&gt;&lt;metaData&gt;&lt;entries&gt;&lt;entry&gt;&lt;key&gt;registratie.version&lt;/key&gt;&lt;value xmlns:xsi="http://www.w3.org/2001/XMLSchema-instance" xmlns:xs="http://www.w3.org/2001/XMLSchema" xsi:type="xs:string"&gt;unspecified&lt;/value&gt;&lt;/entry&gt;&lt;entry&gt;&lt;key&gt;datatypes.version&lt;/key&gt;&lt;value xmlns:xsi="http://www.w3.org/2001/XMLSchema-instance" xmlns:xs="http://www.w3.org/2001/XMLSchema" xsi:type="xs:string"&gt;1.0.184&lt;/value&gt;&lt;/entry&gt;&lt;entry&gt;&lt;key&gt;event.version&lt;/key&gt;&lt;value xmlns:xsi="http://www.w3.org/2001/XMLSchema-instance" xmlns:xs="http://www.w3.org/2001/XMLSchema" xsi:type="xs:string"&gt;1.0.85&lt;/value&gt;&lt;/entry&gt;&lt;entry&gt;&lt;key&gt;axon.version&lt;/key&gt;&lt;value xmlns:xsi="http://www.w3.org/2001/XMLSchema-instance" xmlns:xs="http://www.w3.org/2001/XMLSchema" xsi:type="xs:string"&gt;4.5.9&lt;/value&gt;&lt;/entry&gt;&lt;/entries&gt;&lt;/metaData&gt;</metaData>
        <payload>&lt;?xml version="1.0" encoding="UTF-8" standalone="yes"?&gt;&lt;ns2:tiaStukVerwerkt xmlns:ns2="http://www.kadaster.nl/koers/registratie/event/stuk/rechtsfeit"&gt;&lt;eventIdentificatie&gt;&lt;aggregateId&gt;NL.IMKAD.TIAStuk.900&lt;/aggregateId&gt;&lt;logischTijdstip&gt;2017-07-27T12:17:58.000+02:00&lt;/logischTijdstip&gt;&lt;onderhandenStuk&gt;NL.IMKAD.TIAStuk.900&lt;/onderhandenStuk&gt;&lt;/eventIdentificatie&gt;&lt;deelEnNummer&gt;&lt;soortRegister&gt;&lt;code&gt;2&lt;/code&gt;&lt;waarde&gt;Onroerende Zaken&lt;/waarde&gt;&lt;/soortRegister&gt;&lt;registercode&gt;&lt;code&gt;2&lt;/code&gt;&lt;waarde&gt;Hyp4&lt;/waarde&gt;&lt;/registercode&gt;&lt;deel&gt;61111&lt;/deel&gt;&lt;nummer&gt;33&lt;/nummer&gt;&lt;/deelEnNummer&gt;&lt;statusStukOR&gt;&lt;code&gt;3&lt;/code&gt;&lt;waarde&gt;Ingeschreven&lt;/waarde&gt;&lt;/statusStukOR&gt;&lt;tijdstipAanbieding&gt;2017-07-27T12:17:58.000+02:00&lt;/tijdstipAanbieding&gt;&lt;tijdstipOndertekening&gt;2017-07-27T12:16:58.000+02:00&lt;/tijdstipOndertekening&gt;&lt;aardAangebodenStuk&gt;&lt;code&gt;7&lt;/code&gt;&lt;waarde&gt;Overig&lt;/waarde&gt;&lt;/aardAangebodenStuk&gt;&lt;tekeningIngeschreven&gt;false&lt;/tekeningIngeschreven&gt;&lt;/ns2:tiaStukVerwerkt&gt;</payload>
        <payloadType>nl.kadaster.koers.event.stuk.rechtsfeit.TIAStukVerwerkt</payloadType>
        <payloadRevision>2</payloadRevision>
        <timestamp>2017-07-27T13:17:58.000+02:00</timestamp>
    </event>
    <event>
        <aggregateIdentifier>NL.IMKAD.TIAStuk.900</aggregateIdentifier>
        <sequenceNumber>1</sequenceNumber>
        <type>TIAStuk</type>
        <identifier>98f48eb4-7e4e-4c8e-8966-66b35d29efc6</identifier>
        <metaData>&lt;?xml version="1.0" encoding="UTF-8" standalone="yes"?&gt;&lt;metaData&gt;&lt;entries&gt;&lt;entry&gt;&lt;key&gt;registratie.version&lt;/key&gt;&lt;value xmlns:xsi="http://www.w3.org/2001/XMLSchema-instance" xmlns:xs="http://www.w3.org/2001/XMLSchema" xsi:type="xs:string"&gt;unspecified&lt;/value&gt;&lt;/entry&gt;&lt;entry&gt;&lt;key&gt;datatypes.version&lt;/key&gt;&lt;value xmlns:xsi="http://www.w3.org/2001/XMLSchema-instance" xmlns:xs="http://www.w3.org/2001/XMLSchema" xsi:type="xs:string"&gt;1.0.184&lt;/value&gt;&lt;/entry&gt;&lt;entry&gt;&lt;key&gt;event.version&lt;/key&gt;&lt;value xmlns:xsi="http://www.w3.org/2001/XMLSchema-instance" xmlns:xs="http://www.w3.org/2001/XMLSchema" xsi:type="xs:string"&gt;1.0.85&lt;/value&gt;&lt;/entry&gt;&lt;entry&gt;&lt;key&gt;axon.version&lt;/key&gt;&lt;value xmlns:xsi="http://www.w3.org/2001/XMLSchema-instance" xmlns:xs="http://www.w3.org/2001/XMLSchema" xsi:type="xs:string"&gt;4.5.9&lt;/value&gt;&lt;/entry&gt;&lt;/entries&gt;&lt;/metaData&gt;</metaData>
        <payload>&lt;?xml version="1.0" encoding="UTF-8" standalone="yes"?&gt;&lt;ns2:stukdeelOnderkend xmlns:ns2="http://www.kadaster.nl/koers/registratie/event/stuk/rechtsfeit"&gt;&lt;eventIdentificatie&gt;&lt;aggregateId&gt;NL.IMKAD.TIAStuk.900&lt;/aggregateId&gt;&lt;logischTijdstip&gt;2017-07-27T12:17:58.000+02:00&lt;/logischTijdstip&gt;&lt;onderhandenStuk&gt;NL.IMKAD.TIAStuk.900&lt;/onderhandenStuk&gt;&lt;onderhandenStukdeel&gt;NL.IMKAD.Stukdeel.901&lt;/onderhandenStukdeel&gt;&lt;formeelStuk&gt;NL.IMKAD.TIAStuk.900&lt;/formeelStuk&gt;&lt;formeelStukdeel&gt;NL.IMKAD.Stukdeel.901&lt;/formeelStukdeel&gt;&lt;/eventIdentificatie&gt;&lt;stukdeelId&gt;NL.IMKAD.Stukdeel.901&lt;/stukdeelId&gt;&lt;aard&gt;&lt;code&gt;566&lt;/code&gt;&lt;waarde&gt;Registratie eigendom netwerk&lt;/waarde&gt;&lt;/aard&gt;&lt;/ns2:stukdeelOnderkend&gt;</payload>
        <payloadType>nl.kadaster.koers.event.stuk.rechtsfeit.StukdeelOnderkend</payloadType>
        <payloadRevision>1</payloadRevision>
        <timestamp>2017-07-27T13:17:58.000+02:00</timestamp>
    </event>
    <event>
        <aggregateIdentifier>NL.IMKAD.KadastraalObject.305</aggregateIdentifier>
        <sequenceNumber>0</sequenceNumber>
        <type>Leidingnetwerk</type>
        <identifier>0bd77d74-c68d-4bbe-b49b-ebc170df157d</identifier>
        <metaData>&lt;?xml version="1.0" encoding="UTF-8" standalone="yes"?&gt;&lt;metaData&gt;&lt;entries&gt;&lt;entry&gt;&lt;key&gt;registratie.version&lt;/key&gt;&lt;value xmlns:xsi="http://www.w3.org/2001/XMLSchema-instance" xmlns:xs="http://www.w3.org/2001/XMLSchema" xsi:type="xs:string"&gt;unspecified&lt;/value&gt;&lt;/entry&gt;&lt;entry&gt;&lt;key&gt;datatypes.version&lt;/key&gt;&lt;value xmlns:xsi="http://www.w3.org/2001/XMLSchema-instance" xmlns:xs="http://www.w3.org/2001/XMLSchema" xsi:type="xs:string"&gt;1.0.184&lt;/value&gt;&lt;/entry&gt;&lt;entry&gt;&lt;key&gt;event.version&lt;/key&gt;&lt;value xmlns:xsi="http://www.w3.org/2001/XMLSchema-instance" xmlns:xs="http://www.w3.org/2001/XMLSchema" xsi:type="xs:string"&gt;1.0.85&lt;/value&gt;&lt;/entry&gt;&lt;entry&gt;&lt;key&gt;axon.version&lt;/key&gt;&lt;value xmlns:xsi="http://www.w3.org/2001/XMLSchema-instance" xmlns:xs="http://www.w3.org/2001/XMLSchema" xsi:type="xs:string"&gt;4.5.9&lt;/value&gt;&lt;/entry&gt;&lt;/entries&gt;&lt;/metaData&gt;</metaData>
        <payload>&lt;?xml version="1.0" encoding="UTF-8" standalone="yes"?&gt;&lt;ns2:leidingnetwerkOntstaan xmlns:ns2="http://www.kadaster.nl/koers/registratie/event/kadastraalobject/rechtsfeit"&gt;&lt;eventIdentificatie&gt;&lt;aggregateId&gt;NL.IMKAD.KadastraalObject.305&lt;/aggregateId&gt;&lt;logischTijdstip&gt;2017-07-27T12:17:58.000+02:00&lt;/logischTijdstip&gt;&lt;onderhandenStuk&gt;NL.IMKAD.TIAStuk.900&lt;/onderhandenStuk&gt;&lt;onderhandenStukdeel&gt;NL.IMKAD.Stukdeel.901&lt;/onderhandenStukdeel&gt;&lt;formeelStuk&gt;NL.IMKAD.TIAStuk.900&lt;/formeelStuk&gt;&lt;formeelStukdeel&gt;NL.IMKAD.Stukdeel.901&lt;/formeelStukdeel&gt;&lt;/eventIdentificatie&gt;&lt;kadastraleAanduiding&gt;&lt;kadastraleGemeente&gt;&lt;code&gt;655&lt;/code&gt;&lt;waarde&gt;Netwerken&lt;/waarde&gt;&lt;/kadastraleGemeente&gt;&lt;sectie&gt;S&lt;/sectie&gt;&lt;perceelNummer&gt;79&lt;/perceelNummer&gt;&lt;/kadastraleAanduiding&gt;&lt;eigendomId&gt;NL.IMKAD.ZakelijkRecht.1000&lt;/eigendomId&gt;&lt;aard&gt;&lt;code&gt;S&lt;/code&gt;&lt;waarde&gt;Stadsverwarming&lt;/waarde&gt;&lt;/aard&gt;&lt;uniekIdentificeerbaarNummer&gt;12345&lt;/uniekIdentificeerbaarNummer&gt;&lt;omschrijving&gt;Stadsverwarmingsnetwerk bedrijvigheid&lt;/omschrijving&gt;&lt;/ns2:leidingnetwerkOntstaan&gt;</payload>
        <payloadType>nl.kadaster.koers.event.kadastraalobject.rechtsfeit.LeidingnetwerkOntstaan</payloadType>
        <payloadRevision>1</payloadRevision>
        <timestamp>2017-07-27T13:17:58.000+02:00</timestamp>
    </event>
    <event>
        <aggregateIdentifier>NL.IMKAD.KadastraalObject.305</aggregateIdentifier>
        <sequenceNumber>1</sequenceNumber>
        <type>Leidingnetwerk</type>
        <identifier>a5dac6cf-ef43-4888-a4fa-e7a767f2f4e8</identifier>
        <metaData>&lt;?xml version="1.0" encoding="UTF-8" standalone="yes"?&gt;&lt;metaData&gt;&lt;entries&gt;&lt;entry&gt;&lt;key&gt;registratie.version&lt;/key&gt;&lt;value xmlns:xsi="http://www.w3.org/2001/XMLSchema-instance" xmlns:xs="http://www.w3.org/2001/XMLSchema" xsi:type="xs:string"&gt;unspecified&lt;/value&gt;&lt;/entry&gt;&lt;entry&gt;&lt;key&gt;datatypes.version&lt;/key&gt;&lt;value xmlns:xsi="http://www.w3.org/2001/XMLSchema-instance" xmlns:xs="http://www.w3.org/2001/XMLSchema" xsi:type="xs:string"&gt;1.0.184&lt;/value&gt;&lt;/entry&gt;&lt;entry&gt;&lt;key&gt;event.version&lt;/key&gt;&lt;value xmlns:xsi="http://www.w3.org/2001/XMLSchema-instance" xmlns:xs="http://www.w3.org/2001/XMLSchema" xsi:type="xs:string"&gt;1.0.85&lt;/value&gt;&lt;/entry&gt;&lt;entry&gt;&lt;key&gt;axon.version&lt;/key&gt;&lt;value xmlns:xsi="http://www.w3.org/2001/XMLSchema-instance" xmlns:xs="http://www.w3.org/2001/XMLSchema" xsi:type="xs:string"&gt;4.5.9&lt;/value&gt;&lt;/entry&gt;&lt;/entries&gt;&lt;/metaData&gt;</metaData>
        <payload>&lt;?xml version="1.0" encoding="UTF-8" standalone="yes"?&gt;&lt;ns2:zakelijkRechtTenaamgesteld xmlns:ns2="http://www.kadaster.nl/koers/registratie/event/kadastraalobject/rechtsfeit"&gt;&lt;eventIdentificatie&gt;&lt;aggregateId&gt;NL.IMKAD.KadastraalObject.305&lt;/aggregateId&gt;&lt;logischTijdstip&gt;2017-07-27T12:17:58.000+02:00&lt;/logischTijdstip&gt;&lt;onderhandenStuk&gt;NL.IMKAD.TIAStuk.900&lt;/onderhandenStuk&gt;&lt;onderhandenStukdeel&gt;NL.IMKAD.Stukdeel.901&lt;/onderhandenStukdeel&gt;&lt;formeelStuk&gt;NL.IMKAD.TIAStuk.900&lt;/formeelStuk&gt;&lt;formeelStukdeel&gt;NL.IMKAD.Stukdeel.901&lt;/formeelStukdeel&gt;&lt;/eventIdentificatie&gt;&lt;van&gt;NL.IMKAD.ZakelijkRecht.1000&lt;/van&gt;&lt;verkregenAandelen&gt;&lt;aandeel&gt;&lt;aandeelId&gt;NL.IMKAD.Aandeel.1000&lt;/aandeelId&gt;&lt;aandeel&gt;&lt;teller&gt;1&lt;/teller&gt;&lt;noemer&gt;1&lt;/noemer&gt;&lt;/aandeel&gt;&lt;geldtVoor&gt;&lt;tenaamstelling&gt;&lt;tenaamstellingId&gt;NL.IMKAD.Tenaamstelling.1000&lt;/tenaamstellingId&gt;&lt;tenNameVan&gt;NL.IMKAD.Persoon.26&lt;/tenNameVan&gt;&lt;/tenaamstelling&gt;&lt;/geldtVoor&gt;&lt;/aandeel&gt;&lt;/verkregenAandelen&gt;&lt;/ns2:zakelijkRechtTenaamgesteld&gt;</payload>
        <payloadType>nl.kadaster.koers.event.kadastraalobject.rechtsfeit.ZakelijkRechtTenaamgesteld</payloadType>
        <payloadRevision>1</payloadRevision>
        <timestamp>2017-07-27T13:17:58.000+02:00</timestamp>
    </event>
    <event>
        <aggregateIdentifier>NL.IMKAD.KadastraalObject.305</aggregateIdentifier>
        <sequenceNumber>2</sequenceNumber>
        <type>Leidingnetwerk</type>
        <identifier>293069c7-652d-42f8-862c-58c7cc16d940</identifier>
        <metaData>&lt;?xml version="1.0" encoding="UTF-8" standalone="yes"?&gt;&lt;metaData&gt;&lt;entries&gt;&lt;entry&gt;&lt;key&gt;registratie.version&lt;/key&gt;&lt;value xmlns:xsi="http://www.w3.org/2001/XMLSchema-instance" xmlns:xs="http://www.w3.org/2001/XMLSchema" xsi:type="xs:string"&gt;unspecified&lt;/value&gt;&lt;/entry&gt;&lt;entry&gt;&lt;key&gt;datatypes.version&lt;/key&gt;&lt;value xmlns:xsi="http://www.w3.org/2001/XMLSchema-instance" xmlns:xs="http://www.w3.org/2001/XMLSchema" xsi:type="xs:string"&gt;1.0.184&lt;/value&gt;&lt;/entry&gt;&lt;entry&gt;&lt;key&gt;event.version&lt;/key&gt;&lt;value xmlns:xsi="http://www.w3.org/2001/XMLSchema-instance" xmlns:xs="http://www.w3.org/2001/XMLSchema" xsi:type="xs:string"&gt;1.0.85&lt;/value&gt;&lt;/entry&gt;&lt;entry&gt;&lt;key&gt;axon.version&lt;/key&gt;&lt;value xmlns:xsi="http://www.w3.org/2001/XMLSchema-instance" xmlns:xs="http://www.w3.org/2001/XMLSchema" xsi:type="xs:string"&gt;4.5.9&lt;/value&gt;&lt;/entry&gt;&lt;/entries&gt;&lt;/metaData&gt;</metaData>
        <payload>&lt;?xml version="1.0" encoding="UTF-8" standalone="yes"?&gt;&lt;ns2:stukBijKadastraalObjectAangetekend xmlns:ns2="http://www.kadaster.nl/koers/registratie/event/kadastraalobject/rechtsfeit"&gt;&lt;eventIdentificatie&gt;&lt;aggregateId&gt;NL.IMKAD.KadastraalObject.305&lt;/aggregateId&gt;&lt;logischTijdstip&gt;2017-07-27T12:17:58.000+02:00&lt;/logischTijdstip&gt;&lt;onderhandenStuk&gt;NL.IMKAD.TIAStuk.900&lt;/onderhandenStuk&gt;&lt;onderhandenStukdeel&gt;NL.IMKAD.Stukdeel.901&lt;/onderhandenStukdeel&gt;&lt;formeelStuk&gt;NL.IMKAD.TIAStuk.900&lt;/formeelStuk&gt;&lt;formeelStukdeel&gt;NL.IMKAD.Stukdeel.901&lt;/formeelStukdeel&gt;&lt;/eventIdentificatie&gt;&lt;aantekeningId&gt;NL.IMKAD.Aantekening.1000&lt;/aantekeningId&gt;&lt;aard&gt;&lt;code&gt;113&lt;/code&gt;&lt;waarde&gt;Aanvang registratieprocedure (art. 155a, ONBW)&lt;/waarde&gt;&lt;/aard&gt;&lt;/ns2:stukBijKadastraalObjectAangetekend&gt;</payload>
        <payloadType>nl.kadaster.koers.event.kadastraalobject.rechtsfeit.StukBijKadastraalObjectAangetekend</payloadType>
        <payloadRevision>1</payloadRevision>
        <timestamp>2017-07-27T13:17:58.000+02:00</timestamp>
    </event>
    <event>
        <aggregateIdentifier>NL.IMKAD.TIAStuk.900</aggregateIdentifier>
        <sequenceNumber>2</sequenceNumber>
        <type>TIAStuk</type>
        <identifier>637e3a5c-fc03-4a6d-8197-5f2e0d53c6ee</identifier>
        <metaData>&lt;?xml version="1.0" encoding="UTF-8" standalone="yes"?&gt;&lt;metaData&gt;&lt;entries&gt;&lt;entry&gt;&lt;key&gt;registratie.version&lt;/key&gt;&lt;value xmlns:xsi="http://www.w3.org/2001/XMLSchema-instance" xmlns:xs="http://www.w3.org/2001/XMLSchema" xsi:type="xs:string"&gt;unspecified&lt;/value&gt;&lt;/entry&gt;&lt;entry&gt;&lt;key&gt;datatypes.version&lt;/key&gt;&lt;value xmlns:xsi="http://www.w3.org/2001/XMLSchema-instance" xmlns:xs="http://www.w3.org/2001/XMLSchema" xsi:type="xs:string"&gt;1.0.184&lt;/value&gt;&lt;/entry&gt;&lt;entry&gt;&lt;key&gt;event.version&lt;/key&gt;&lt;value xmlns:xsi="http://www.w3.org/2001/XMLSchema-instance" xmlns:xs="http://www.w3.org/2001/XMLSchema" xsi:type="xs:string"&gt;1.0.85&lt;/value&gt;&lt;/entry&gt;&lt;entry&gt;&lt;key&gt;axon.version&lt;/key&gt;&lt;value xmlns:xsi="http://www.w3.org/2001/XMLSchema-instance" xmlns:xs="http://www.w3.org/2001/XMLSchema" xsi:type="xs:string"&gt;4.5.9&lt;/value&gt;&lt;/entry&gt;&lt;/entries&gt;&lt;/metaData&gt;</metaData>
        <payload>&lt;?xml version="1.0" encoding="UTF-8" standalone="yes"?&gt;&lt;ns2:stukTransactieAfgerond xmlns:ns2="http://www.kadaster.nl/koers/registratie/event/stuk/technisch"&gt;&lt;eventIdentificatie&gt;&lt;aggregateId&gt;NL.IMKAD.TIAStuk.900&lt;/aggregateId&gt;&lt;logischTijdstip&gt;2017-07-27T12:17:58.000+02:00&lt;/logischTijdstip&gt;&lt;onderhandenStuk&gt;NL.IMKAD.TIAStuk.900&lt;/onderhandenStuk&gt;&lt;/eventIdentificatie&gt;&lt;verwerkingsResultaat&gt;VOLLEDIG_VERWERKT_STUK&lt;/verwerkingsResultaat&gt;&lt;stukUitgesloten&gt;false&lt;/stukUitgesloten&gt;&lt;kadastraalObjectIdentificaties&gt;&lt;kadastraalObjectIdentificatie&gt;&lt;uuid&gt;Netwerken-S79&lt;/uuid&gt;&lt;kadastraleAanduiding&gt;&lt;kadastraleGemeente&gt;&lt;code&gt;655&lt;/code&gt;&lt;waarde&gt;Netwerken&lt;/waarde&gt;&lt;/kadastraleGemeente&gt;&lt;sectie&gt;S&lt;/sectie&gt;&lt;perceelNummer&gt;79&lt;/perceelNummer&gt;&lt;/kadastraleAanduiding&gt;&lt;kadastraalObjectId&gt;NL.IMKAD.KadastraalObject.305&lt;/kadastraalObjectId&gt;&lt;/kadastraalObjectIdentificatie&gt;&lt;/kadastraalObjectIdentificaties&gt;&lt;/ns2:stukTransactieAfgerond&gt;</payload>
        <payloadType>nl.kadaster.koers.event.stuk.technisch.StukTransactieAfgerond</payloadType>
        <payloadRevision>2</payloadRevision>
        <timestamp>2017-07-27T13:17:58.000+02:00</timestamp>
    </event>
    <event>
        <aggregateIdentifier>NL.IMKAD.TIAStuk.100</aggregateIdentifier>
        <sequenceNumber>0</sequenceNumber>
        <type>TIAStuk</type>
        <identifier>7fc691b3-3525-4577-9eab-b34f2ab6fe2a</identifier>
        <metaData>&lt;?xml version="1.0" encoding="UTF-8" standalone="yes"?&gt;&lt;metaData&gt;&lt;entries&gt;&lt;entry&gt;&lt;key&gt;registratie.version&lt;/key&gt;&lt;value xmlns:xsi="http://www.w3.org/2001/XMLSchema-instance" xmlns:xs="http://www.w3.org/2001/XMLSchema" xsi:type="xs:string"&gt;unspecified&lt;/value&gt;&lt;/entry&gt;&lt;entry&gt;&lt;key&gt;datatypes.version&lt;/key&gt;&lt;value xmlns:xsi="http://www.w3.org/2001/XMLSchema-instance" xmlns:xs="http://www.w3.org/2001/XMLSchema" xsi:type="xs:string"&gt;1.0.184&lt;/value&gt;&lt;/entry&gt;&lt;entry&gt;&lt;key&gt;event.version&lt;/key&gt;&lt;value xmlns:xsi="http://www.w3.org/2001/XMLSchema-instance" xmlns:xs="http://www.w3.org/2001/XMLSchema" xsi:type="xs:string"&gt;1.0.85&lt;/value&gt;&lt;/entry&gt;&lt;entry&gt;&lt;key&gt;axon.version&lt;/key&gt;&lt;value xmlns:xsi="http://www.w3.org/2001/XMLSchema-instance" xmlns:xs="http://www.w3.org/2001/XMLSchema" xsi:type="xs:string"&gt;4.5.9&lt;/value&gt;&lt;/entry&gt;&lt;/entries&gt;&lt;/metaData&gt;</metaData>
        <payload>&lt;?xml version="1.0" encoding="UTF-8" standalone="yes"?&gt;&lt;ns2:tiaStukVerwerkt xmlns:ns2="http://www.kadaster.nl/koers/registratie/event/stuk/rechtsfeit"&gt;&lt;eventIdentificatie&gt;&lt;aggregateId&gt;NL.IMKAD.TIAStuk.100&lt;/aggregateId&gt;&lt;logischTijdstip&gt;2017-07-26T09:00:00.000+02:00&lt;/logischTijdstip&gt;&lt;onderhandenStuk&gt;NL.IMKAD.TIAStuk.100&lt;/onderhandenStuk&gt;&lt;/eventIdentificatie&gt;&lt;deelEnNummer&gt;&lt;soortRegister&gt;&lt;code&gt;2&lt;/code&gt;&lt;waarde&gt;Onroerende Zaken&lt;/waarde&gt;&lt;/soortRegister&gt;&lt;registercode&gt;&lt;code&gt;2&lt;/code&gt;&lt;waarde&gt;Hyp4&lt;/waarde&gt;&lt;/registercode&gt;&lt;deel&gt;61111&lt;/deel&gt;&lt;nummer&gt;31&lt;/nummer&gt;&lt;/deelEnNummer&gt;&lt;statusStukOR&gt;&lt;code&gt;3&lt;/code&gt;&lt;waarde&gt;Ingeschreven&lt;/waarde&gt;&lt;/statusStukOR&gt;&lt;tijdstipAanbieding&gt;2017-07-26T09:00:00.000+02:00&lt;/tijdstipAanbieding&gt;&lt;tijdstipOndertekening&gt;2017-07-25T15:17:58.000+02:00&lt;/tijdstipOndertekening&gt;&lt;aardAangebodenStuk&gt;&lt;code&gt;7&lt;/code&gt;&lt;waarde&gt;Overig&lt;/waarde&gt;&lt;/aardAangebodenStuk&gt;&lt;tekeningIngeschreven&gt;false&lt;/tekeningIngeschreven&gt;&lt;/ns2:tiaStukVerwerkt&gt;</payload>
        <payloadType>nl.kadaster.koers.event.stuk.rechtsfeit.TIAStukVerwerkt</payloadType>
        <payloadRevision>2</payloadRevision>
        <timestamp>2017-07-27T14:17:58.000+02:00</timestamp>
    </event>
    <event>
        <aggregateIdentifier>NL.IMKAD.TIAStuk.100</aggregateIdentifier>
        <sequenceNumber>1</sequenceNumber>
        <type>TIAStuk</type>
        <identifier>99847fec-c132-4196-ae42-8e117feaa350</identifier>
        <metaData>&lt;?xml version="1.0" encoding="UTF-8" standalone="yes"?&gt;&lt;metaData&gt;&lt;entries&gt;&lt;entry&gt;&lt;key&gt;registratie.version&lt;/key&gt;&lt;value xmlns:xsi="http://www.w3.org/2001/XMLSchema-instance" xmlns:xs="http://www.w3.org/2001/XMLSchema" xsi:type="xs:string"&gt;unspecified&lt;/value&gt;&lt;/entry&gt;&lt;entry&gt;&lt;key&gt;datatypes.version&lt;/key&gt;&lt;value xmlns:xsi="http://www.w3.org/2001/XMLSchema-instance" xmlns:xs="http://www.w3.org/2001/XMLSchema" xsi:type="xs:string"&gt;1.0.184&lt;/value&gt;&lt;/entry&gt;&lt;entry&gt;&lt;key&gt;event.version&lt;/key&gt;&lt;value xmlns:xsi="http://www.w3.org/2001/XMLSchema-instance" xmlns:xs="http://www.w3.org/2001/XMLSchema" xsi:type="xs:string"&gt;1.0.85&lt;/value&gt;&lt;/entry&gt;&lt;entry&gt;&lt;key&gt;axon.version&lt;/key&gt;&lt;value xmlns:xsi="http://www.w3.org/2001/XMLSchema-instance" xmlns:xs="http://www.w3.org/2001/XMLSchema" xsi:type="xs:string"&gt;4.5.9&lt;/value&gt;&lt;/entry&gt;&lt;/entries&gt;&lt;/metaData&gt;</metaData>
        <payload>&lt;?xml version="1.0" encoding="UTF-8" standalone="yes"?&gt;&lt;ns2:stukdeelLeveringOnderkend xmlns:ns2="http://www.kadaster.nl/koers/registratie/event/stuk/rechtsfeit"&gt;&lt;eventIdentificatie&gt;&lt;aggregateId&gt;NL.IMKAD.TIAStuk.100&lt;/aggregateId&gt;&lt;logischTijdstip&gt;2017-07-26T09:00:00.000+02:00&lt;/logischTijdstip&gt;&lt;onderhandenStuk&gt;NL.IMKAD.TIAStuk.100&lt;/onderhandenStuk&gt;&lt;onderhandenStukdeel&gt;NL.IMKAD.Stukdeel.101&lt;/onderhandenStukdeel&gt;&lt;formeelStuk&gt;NL.IMKAD.TIAStuk.100&lt;/formeelStuk&gt;&lt;formeelStukdeel&gt;NL.IMKAD.Stukdeel.101&lt;/formeelStukdeel&gt;&lt;/eventIdentificatie&gt;&lt;stukdeelId&gt;NL.IMKAD.Stukdeel.101&lt;/stukdeelId&gt;&lt;aard&gt;&lt;code&gt;606&lt;/code&gt;&lt;waarde&gt;Overdracht (eigendom en/of beperkt recht)&lt;/waarde&gt;&lt;/aard&gt;&lt;omschrijvingKadastraleObjecten&gt;huis met tuin&lt;/omschrijvingKadastraleObjecten&gt;&lt;/ns2:stukdeelLeveringOnderkend&gt;</payload>
        <payloadType>nl.kadaster.koers.event.stuk.rechtsfeit.StukdeelLeveringOnderkend</payloadType>
        <payloadRevision>1</payloadRevision>
        <timestamp>2017-07-27T14:17:58.000+02:00</timestamp>
    </event>
    <event>
        <aggregateIdentifier>NL.IMKAD.KadastraalObject.100</aggregateIdentifier>
        <sequenceNumber>0</sequenceNumber>
        <type>Perceel</type>
        <identifier>b58a166d-df7e-4eb9-b11e-0bb439d63d7e</identifier>
        <metaData>&lt;?xml version="1.0" encoding="UTF-8" standalone="yes"?&gt;&lt;metaData&gt;&lt;entries&gt;&lt;entry&gt;&lt;key&gt;registratie.version&lt;/key&gt;&lt;value xmlns:xsi="http://www.w3.org/2001/XMLSchema-instance" xmlns:xs="http://www.w3.org/2001/XMLSchema" xsi:type="xs:string"&gt;unspecified&lt;/value&gt;&lt;/entry&gt;&lt;entry&gt;&lt;key&gt;datatypes.version&lt;/key&gt;&lt;value xmlns:xsi="http://www.w3.org/2001/XMLSchema-instance" xmlns:xs="http://www.w3.org/2001/XMLSchema" xsi:type="xs:string"&gt;1.0.184&lt;/value&gt;&lt;/entry&gt;&lt;entry&gt;&lt;key&gt;event.version&lt;/key&gt;&lt;value xmlns:xsi="http://www.w3.org/2001/XMLSchema-instance" xmlns:xs="http://www.w3.org/2001/XMLSchema" xsi:type="xs:string"&gt;1.0.85&lt;/value&gt;&lt;/entry&gt;&lt;entry&gt;&lt;key&gt;axon.version&lt;/key&gt;&lt;value xmlns:xsi="http://www.w3.org/2001/XMLSchema-instance" xmlns:xs="http://www.w3.org/2001/XMLSchema" xsi:type="xs:string"&gt;4.5.9&lt;/value&gt;&lt;/entry&gt;&lt;/entries&gt;&lt;/metaData&gt;</metaData>
        <payload>&lt;?xml version="1.0" encoding="UTF-8" standalone="yes"?&gt;&lt;ns2:perceelOntstaan xmlns:ns2="http://www.kadaster.nl/koers/registratie/event/kadastraalobject/rechtsfeit"&gt;&lt;eventIdentificatie&gt;&lt;aggregateId&gt;NL.IMKAD.KadastraalObject.100&lt;/aggregateId&gt;&lt;logischTijdstip&gt;2017-07-26T09:00:00.000+02:00&lt;/logischTijdstip&gt;&lt;onderhandenStuk&gt;NL.IMKAD.TIAStuk.100&lt;/onderhandenStuk&gt;&lt;onderhandenStukdeel&gt;NL.IMKAD.Stukdeel.101&lt;/onderhandenStukdeel&gt;&lt;formeelStuk&gt;NL.IMKAD.TIAStuk.100&lt;/formeelStuk&gt;&lt;formeelStukdeel&gt;NL.IMKAD.Stukdeel.101&lt;/formeelStukdeel&gt;&lt;/eventIdentificatie&gt;&lt;kadastraleAanduiding&gt;&lt;kadastraleGemeente&gt;&lt;code&gt;50&lt;/code&gt;&lt;waarde&gt;Apeldoorn&lt;/waarde&gt;&lt;/kadastraleGemeente&gt;&lt;sectie&gt;H&lt;/sectie&gt;&lt;perceelNummer&gt;2404&lt;/perceelNummer&gt;&lt;/kadastraleAanduiding&gt;&lt;eigendomId&gt;NL.IMKAD.ZakelijkRecht.1001&lt;/eigendomId&gt;&lt;classificatie&gt;&lt;code&gt;3&lt;/code&gt;&lt;waarde&gt;Definitief perceel&lt;/waarde&gt;&lt;/classificatie&gt;&lt;kadastraleGrootte&gt;&lt;soortGrootte&gt;&lt;code&gt;1&lt;/code&gt;&lt;waarde&gt;Vastgesteld&lt;/waarde&gt;&lt;/soortGrootte&gt;&lt;waarde&gt;&lt;hectare&gt;0&lt;/hectare&gt;&lt;are&gt;10&lt;/are&gt;&lt;centiare&gt;0&lt;/centiare&gt;&lt;/waarde&gt;&lt;/kadastraleGrootte&gt;&lt;coordinaten&gt;155698.552 285087.847&lt;/coordinaten&gt;&lt;/ns2:perceelOntstaan&gt;</payload>
        <payloadType>nl.kadaster.koers.event.kadastraalobject.rechtsfeit.PerceelOntstaan</payloadType>
        <payloadRevision>1</payloadRevision>
        <timestamp>2017-07-27T14:17:58.000+02:00</timestamp>
    </event>
    <event>
        <aggregateIdentifier>NL.IMKAD.KadastraalObject.100</aggregateIdentifier>
        <sequenceNumber>1</sequenceNumber>
        <type>Perceel</type>
        <identifier>f85521ef-a9e7-4442-bbac-93eb62115785</identifier>
        <metaData>&lt;?xml version="1.0" encoding="UTF-8" standalone="yes"?&gt;&lt;metaData&gt;&lt;entries&gt;&lt;entry&gt;&lt;key&gt;registratie.version&lt;/key&gt;&lt;value xmlns:xsi="http://www.w3.org/2001/XMLSchema-instance" xmlns:xs="http://www.w3.org/2001/XMLSchema" xsi:type="xs:string"&gt;unspecified&lt;/value&gt;&lt;/entry&gt;&lt;entry&gt;&lt;key&gt;datatypes.version&lt;/key&gt;&lt;value xmlns:xsi="http://www.w3.org/2001/XMLSchema-instance" xmlns:xs="http://www.w3.org/2001/XMLSchema" xsi:type="xs:string"&gt;1.0.184&lt;/value&gt;&lt;/entry&gt;&lt;entry&gt;&lt;key&gt;event.version&lt;/key&gt;&lt;value xmlns:xsi="http://www.w3.org/2001/XMLSchema-instance" xmlns:xs="http://www.w3.org/2001/XMLSchema" xsi:type="xs:string"&gt;1.0.85&lt;/value&gt;&lt;/entry&gt;&lt;entry&gt;&lt;key&gt;axon.version&lt;/key&gt;&lt;value xmlns:xsi="http://www.w3.org/2001/XMLSchema-instance" xmlns:xs="http://www.w3.org/2001/XMLSchema" xsi:type="xs:string"&gt;4.5.9&lt;/value&gt;&lt;/entry&gt;&lt;/entries&gt;&lt;/metaData&gt;</metaData>
        <payload>&lt;?xml version="1.0" encoding="UTF-8" standalone="yes"?&gt;&lt;ns2:koopsomEnCultuurGewijzigd xmlns:ns2="http://www.kadaster.nl/koers/registratie/event/kadastraalobject/rechtsfeit"&gt;&lt;eventIdentificatie&gt;&lt;aggregateId&gt;NL.IMKAD.KadastraalObject.100&lt;/aggregateId&gt;&lt;logischTijdstip&gt;2017-07-26T09:00:00.000+02:00&lt;/logischTijdstip&gt;&lt;onderhandenStuk&gt;NL.IMKAD.TIAStuk.100&lt;/onderhandenStuk&gt;&lt;onderhandenStukdeel&gt;NL.IMKAD.Stukdeel.101&lt;/onderhandenStukdeel&gt;&lt;formeelStuk&gt;NL.IMKAD.TIAStuk.100&lt;/formeelStuk&gt;&lt;formeelStukdeel&gt;NL.IMKAD.Stukdeel.101&lt;/formeelStukdeel&gt;&lt;/eventIdentificatie&gt;&lt;koopsom&gt;&lt;bedrag&gt;&lt;som&gt;200000.00&lt;/som&gt;&lt;valuta&gt;&lt;code&gt;EUR&lt;/code&gt;&lt;waarde&gt;Euro&lt;/waarde&gt;&lt;/valuta&gt;&lt;/bedrag&gt;&lt;meerObjecten&gt;false&lt;/meerObjecten&gt;&lt;koopjaar&gt;2017&lt;/koopjaar&gt;&lt;/koopsom&gt;&lt;aardCultuurOnbebouwd&gt;&lt;code&gt;34&lt;/code&gt;&lt;waarde&gt;Parkeren&lt;/waarde&gt;&lt;/aardCultuurOnbebouwd&gt;&lt;aardCultuurBebouwd&gt;&lt;code&gt;11&lt;/code&gt;&lt;waarde&gt;Wonen&lt;/waarde&gt;&lt;/aardCultuurBebouwd&gt;&lt;/ns2:koopsomEnCultuurGewijzigd&gt;</payload>
        <payloadType>nl.kadaster.koers.event.kadastraalobject.rechtsfeit.KoopsomEnCultuurGewijzigd</payloadType>
        <payloadRevision>1</payloadRevision>
        <timestamp>2017-07-27T14:17:58.000+02:00</timestamp>
    </event>
    <event>
        <aggregateIdentifier>NL.IMKAD.KadastraalObject.100</aggregateIdentifier>
        <sequenceNumber>2</sequenceNumber>
        <type>Perceel</type>
        <identifier>08b3b62c-f92b-4fc0-93e7-d434bc16d58b</identifier>
        <metaData>&lt;?xml version="1.0" encoding="UTF-8" standalone="yes"?&gt;&lt;metaData&gt;&lt;entries&gt;&lt;entry&gt;&lt;key&gt;registratie.version&lt;/key&gt;&lt;value xmlns:xsi="http://www.w3.org/2001/XMLSchema-instance" xmlns:xs="http://www.w3.org/2001/XMLSchema" xsi:type="xs:string"&gt;unspecified&lt;/value&gt;&lt;/entry&gt;&lt;entry&gt;&lt;key&gt;datatypes.version&lt;/key&gt;&lt;value xmlns:xsi="http://www.w3.org/2001/XMLSchema-instance" xmlns:xs="http://www.w3.org/2001/XMLSchema" xsi:type="xs:string"&gt;1.0.184&lt;/value&gt;&lt;/entry&gt;&lt;entry&gt;&lt;key&gt;event.version&lt;/key&gt;&lt;value xmlns:xsi="http://www.w3.org/2001/XMLSchema-instance" xmlns:xs="http://www.w3.org/2001/XMLSchema" xsi:type="xs:string"&gt;1.0.85&lt;/value&gt;&lt;/entry&gt;&lt;entry&gt;&lt;key&gt;axon.version&lt;/key&gt;&lt;value xmlns:xsi="http://www.w3.org/2001/XMLSchema-instance" xmlns:xs="http://www.w3.org/2001/XMLSchema" xsi:type="xs:string"&gt;4.5.9&lt;/value&gt;&lt;/entry&gt;&lt;/entries&gt;&lt;/metaData&gt;</metaData>
        <payload>&lt;?xml version="1.0" encoding="UTF-8" standalone="yes"?&gt;&lt;ns2:zakelijkRechtTenaamgesteld xmlns:ns2="http://www.kadaster.nl/koers/registratie/event/kadastraalobject/rechtsfeit"&gt;&lt;eventIdentificatie&gt;&lt;aggregateId&gt;NL.IMKAD.KadastraalObject.100&lt;/aggregateId&gt;&lt;logischTijdstip&gt;2017-07-26T09:00:00.000+02:00&lt;/logischTijdstip&gt;&lt;onderhandenStuk&gt;NL.IMKAD.TIAStuk.100&lt;/onderhandenStuk&gt;&lt;onderhandenStukdeel&gt;NL.IMKAD.Stukdeel.101&lt;/onderhandenStukdeel&gt;&lt;formeelStuk&gt;NL.IMKAD.TIAStuk.100&lt;/formeelStuk&gt;&lt;formeelStukdeel&gt;NL.IMKAD.Stukdeel.101&lt;/formeelStukdeel&gt;&lt;/eventIdentificatie&gt;&lt;van&gt;NL.IMKAD.ZakelijkRecht.1001&lt;/van&gt;&lt;verkregenAandelen&gt;&lt;aandeel&gt;&lt;aandeelId&gt;NL.IMKAD.Aandeel.1001&lt;/aandeelId&gt;&lt;aandeel&gt;&lt;teller&gt;1&lt;/teller&gt;&lt;noemer&gt;1&lt;/noemer&gt;&lt;/aandeel&gt;&lt;geldtVoor&gt;&lt;tenaamstelling&gt;&lt;tenaamstellingId&gt;NL.IMKAD.Tenaamstelling.1001&lt;/tenaamstellingId&gt;&lt;tenNameVan&gt;NL.IMKAD.Persoon.50&lt;/tenNameVan&gt;&lt;burgerlijkeStaat&gt;&lt;code&gt;2&lt;/code&gt;&lt;waarde&gt;Ongehuwd en geen geregistreerd partnerschap&lt;/waarde&gt;&lt;/burgerlijkeStaat&gt;&lt;/tenaamstelling&gt;&lt;/geldtVoor&gt;&lt;/aandeel&gt;&lt;/verkregenAandelen&gt;&lt;/ns2:zakelijkRechtTenaamgesteld&gt;</payload>
        <payloadType>nl.kadaster.koers.event.kadastraalobject.rechtsfeit.ZakelijkRechtTenaamgesteld</payloadType>
        <payloadRevision>1</payloadRevision>
        <timestamp>2017-07-27T14:17:58.000+02:00</timestamp>
    </event>
    <event>
        <aggregateIdentifier>NL.IMKAD.TIAStuk.100</aggregateIdentifier>
        <sequenceNumber>2</sequenceNumber>
        <type>TIAStuk</type>
        <identifier>bb024bef-2ab7-499f-b776-63241acfb3ce</identifier>
        <metaData>&lt;?xml version="1.0" encoding="UTF-8" standalone="yes"?&gt;&lt;metaData&gt;&lt;entries&gt;&lt;entry&gt;&lt;key&gt;registratie.version&lt;/key&gt;&lt;value xmlns:xsi="http://www.w3.org/2001/XMLSchema-instance" xmlns:xs="http://www.w3.org/2001/XMLSchema" xsi:type="xs:string"&gt;unspecified&lt;/value&gt;&lt;/entry&gt;&lt;entry&gt;&lt;key&gt;datatypes.version&lt;/key&gt;&lt;value xmlns:xsi="http://www.w3.org/2001/XMLSchema-instance" xmlns:xs="http://www.w3.org/2001/XMLSchema" xsi:type="xs:string"&gt;1.0.184&lt;/value&gt;&lt;/entry&gt;&lt;entry&gt;&lt;key&gt;event.version&lt;/key&gt;&lt;value xmlns:xsi="http://www.w3.org/2001/XMLSchema-instance" xmlns:xs="http://www.w3.org/2001/XMLSchema" xsi:type="xs:string"&gt;1.0.85&lt;/value&gt;&lt;/entry&gt;&lt;entry&gt;&lt;key&gt;axon.version&lt;/key&gt;&lt;value xmlns:xsi="http://www.w3.org/2001/XMLSchema-instance" xmlns:xs="http://www.w3.org/2001/XMLSchema" xsi:type="xs:string"&gt;4.5.9&lt;/value&gt;&lt;/entry&gt;&lt;/entries&gt;&lt;/metaData&gt;</metaData>
        <payload>&lt;?xml version="1.0" encoding="UTF-8" standalone="yes"?&gt;&lt;ns2:stukTransactieAfgerond xmlns:ns2="http://www.kadaster.nl/koers/registratie/event/stuk/technisch"&gt;&lt;eventIdentificatie&gt;&lt;aggregateId&gt;NL.IMKAD.TIAStuk.100&lt;/aggregateId&gt;&lt;logischTijdstip&gt;2017-07-26T09:00:00.000+02:00&lt;/logischTijdstip&gt;&lt;onderhandenStuk&gt;NL.IMKAD.TIAStuk.100&lt;/onderhandenStuk&gt;&lt;/eventIdentificatie&gt;&lt;verwerkingsResultaat&gt;VOLLEDIG_VERWERKT_STUK&lt;/verwerkingsResultaat&gt;&lt;stukUitgesloten&gt;false&lt;/stukUitgesloten&gt;&lt;kadastraalObjectIdentificaties&gt;&lt;kadastraalObjectIdentificatie&gt;&lt;uuid&gt;Apeldoorn-H02404&lt;/uuid&gt;&lt;kadastraleAanduiding&gt;&lt;kadastraleGemeente&gt;&lt;code&gt;50&lt;/code&gt;&lt;waarde&gt;Apeldoorn&lt;/waarde&gt;&lt;/kadastraleGemeente&gt;&lt;sectie&gt;H&lt;/sectie&gt;&lt;perceelNummer&gt;2404&lt;/perceelNummer&gt;&lt;/kadastraleAanduiding&gt;&lt;kadastraalObjectId&gt;NL.IMKAD.KadastraalObject.100&lt;/kadastraalObjectId&gt;&lt;/kadastraalObjectIdentificatie&gt;&lt;/kadastraalObjectIdentificaties&gt;&lt;/ns2:stukTransactieAfgerond&gt;</payload>
        <payloadType>nl.kadaster.koers.event.stuk.technisch.StukTransactieAfgerond</payloadType>
        <payloadRevision>2</payloadRevision>
        <timestamp>2017-07-27T14:17:58.000+02:00</timestamp>
    </event>
    <event>
        <aggregateIdentifier>NL.IMKAD.TIAStuk.157</aggregateIdentifier>
        <sequenceNumber>0</sequenceNumber>
        <type>TIAStuk</type>
        <identifier>663715d1-d726-4ca4-b18d-290ecdc3b05c</identifier>
        <metaData>&lt;?xml version="1.0" encoding="UTF-8" standalone="yes"?&gt;&lt;metaData&gt;&lt;entries&gt;&lt;entry&gt;&lt;key&gt;registratie.version&lt;/key&gt;&lt;value xmlns:xsi="http://www.w3.org/2001/XMLSchema-instance" xmlns:xs="http://www.w3.org/2001/XMLSchema" xsi:type="xs:string"&gt;unspecified&lt;/value&gt;&lt;/entry&gt;&lt;entry&gt;&lt;key&gt;datatypes.version&lt;/key&gt;&lt;value xmlns:xsi="http://www.w3.org/2001/XMLSchema-instance" xmlns:xs="http://www.w3.org/2001/XMLSchema" xsi:type="xs:string"&gt;1.0.184&lt;/value&gt;&lt;/entry&gt;&lt;entry&gt;&lt;key&gt;event.version&lt;/key&gt;&lt;value xmlns:xsi="http://www.w3.org/2001/XMLSchema-instance" xmlns:xs="http://www.w3.org/2001/XMLSchema" xsi:type="xs:string"&gt;1.0.85&lt;/value&gt;&lt;/entry&gt;&lt;entry&gt;&lt;key&gt;axon.version&lt;/key&gt;&lt;value xmlns:xsi="http://www.w3.org/2001/XMLSchema-instance" xmlns:xs="http://www.w3.org/2001/XMLSchema" xsi:type="xs:string"&gt;4.5.9&lt;/value&gt;&lt;/entry&gt;&lt;/entries&gt;&lt;/metaData&gt;</metaData>
        <payload>&lt;?xml version="1.0" encoding="UTF-8" standalone="yes"?&gt;&lt;ns2:tiaStukVerwerkt xmlns:ns2="http://www.kadaster.nl/koers/registratie/event/stuk/rechtsfeit"&gt;&lt;eventIdentificatie&gt;&lt;aggregateId&gt;NL.IMKAD.TIAStuk.157&lt;/aggregateId&gt;&lt;logischTijdstip&gt;2017-07-27T12:17:58.000+02:00&lt;/logischTijdstip&gt;&lt;onderhandenStuk&gt;NL.IMKAD.TIAStuk.157&lt;/onderhandenStuk&gt;&lt;/eventIdentificatie&gt;&lt;deelEnNummer&gt;&lt;soortRegister&gt;&lt;code&gt;2&lt;/code&gt;&lt;waarde&gt;Onroerende Zaken&lt;/waarde&gt;&lt;/soortRegister&gt;&lt;registercode&gt;&lt;code&gt;2&lt;/code&gt;&lt;waarde&gt;Hyp4&lt;/waarde&gt;&lt;/registercode&gt;&lt;deel&gt;62346&lt;/deel&gt;&lt;nummer&gt;3&lt;/nummer&gt;&lt;/deelEnNummer&gt;&lt;statusStukOR&gt;&lt;code&gt;3&lt;/code&gt;&lt;waarde&gt;Ingeschreven&lt;/waarde&gt;&lt;/statusStukOR&gt;&lt;tijdstipAanbieding&gt;2017-07-27T12:17:58.000+02:00&lt;/tijdstipAanbieding&gt;&lt;tijdstipOndertekening&gt;2017-07-27T12:16:58.000+02:00&lt;/tijdstipOndertekening&gt;&lt;aardAangebodenStuk&gt;&lt;code&gt;7&lt;/code&gt;&lt;waarde&gt;Overig&lt;/waarde&gt;&lt;/aardAangebodenStuk&gt;&lt;tekeningIngeschreven&gt;false&lt;/tekeningIngeschreven&gt;&lt;/ns2:tiaStukVerwerkt&gt;</payload>
        <payloadType>nl.kadaster.koers.event.stuk.rechtsfeit.TIAStukVerwerkt</payloadType>
        <payloadRevision>2</payloadRevision>
        <timestamp>2017-07-27T15:17:58.000+02:00</timestamp>
    </event>
    <event>
        <aggregateIdentifier>NL.IMKAD.TIAStuk.157</aggregateIdentifier>
        <sequenceNumber>1</sequenceNumber>
        <type>TIAStuk</type>
        <identifier>2b641c92-c1e6-4500-b13d-0656809481c3</identifier>
        <metaData>&lt;?xml version="1.0" encoding="UTF-8" standalone="yes"?&gt;&lt;metaData&gt;&lt;entries&gt;&lt;entry&gt;&lt;key&gt;registratie.version&lt;/key&gt;&lt;value xmlns:xsi="http://www.w3.org/2001/XMLSchema-instance" xmlns:xs="http://www.w3.org/2001/XMLSchema" xsi:type="xs:string"&gt;unspecified&lt;/value&gt;&lt;/entry&gt;&lt;entry&gt;&lt;key&gt;datatypes.version&lt;/key&gt;&lt;value xmlns:xsi="http://www.w3.org/2001/XMLSchema-instance" xmlns:xs="http://www.w3.org/2001/XMLSchema" xsi:type="xs:string"&gt;1.0.184&lt;/value&gt;&lt;/entry&gt;&lt;entry&gt;&lt;key&gt;event.version&lt;/key&gt;&lt;value xmlns:xsi="http://www.w3.org/2001/XMLSchema-instance" xmlns:xs="http://www.w3.org/2001/XMLSchema" xsi:type="xs:string"&gt;1.0.85&lt;/value&gt;&lt;/entry&gt;&lt;entry&gt;&lt;key&gt;axon.version&lt;/key&gt;&lt;value xmlns:xsi="http://www.w3.org/2001/XMLSchema-instance" xmlns:xs="http://www.w3.org/2001/XMLSchema" xsi:type="xs:string"&gt;4.5.9&lt;/value&gt;&lt;/entry&gt;&lt;/entries&gt;&lt;/metaData&gt;</metaData>
        <payload>&lt;?xml version="1.0" encoding="UTF-8" standalone="yes"?&gt;&lt;ns2:stukdeelLeveringOnderkend xmlns:ns2="http://www.kadaster.nl/koers/registratie/event/stuk/rechtsfeit"&gt;&lt;eventIdentificatie&gt;&lt;aggregateId&gt;NL.IMKAD.TIAStuk.157&lt;/aggregateId&gt;&lt;logischTijdstip&gt;2017-07-27T12:17:58.000+02:00&lt;/logischTijdstip&gt;&lt;onderhandenStuk&gt;NL.IMKAD.TIAStuk.157&lt;/onderhandenStuk&gt;&lt;onderhandenStukdeel&gt;NL.IMKAD.Stukdeel.158&lt;/onderhandenStukdeel&gt;&lt;formeelStuk&gt;NL.IMKAD.TIAStuk.157&lt;/formeelStuk&gt;&lt;formeelStukdeel&gt;NL.IMKAD.Stukdeel.158&lt;/formeelStukdeel&gt;&lt;/eventIdentificatie&gt;&lt;stukdeelId&gt;NL.IMKAD.Stukdeel.158&lt;/stukdeelId&gt;&lt;aard&gt;&lt;code&gt;644&lt;/code&gt;&lt;waarde&gt;Vestiging zakelijk recht van opstal nutsvoorzieningen&lt;/waarde&gt;&lt;/aard&gt;&lt;omschrijvingKadastraleObjecten&gt;huis met tuin&lt;/omschrijvingKadastraleObjecten&gt;&lt;bedragTransactiesomLevering&gt;&lt;som&gt;250000.00&lt;/som&gt;&lt;valuta&gt;&lt;code&gt;EUR&lt;/code&gt;&lt;waarde&gt;Euro&lt;/waarde&gt;&lt;/valuta&gt;&lt;/bedragTransactiesomLevering&gt;&lt;/ns2:stukdeelLeveringOnderkend&gt;</payload>
        <payloadType>nl.kadaster.koers.event.stuk.rechtsfeit.StukdeelLeveringOnderkend</payloadType>
        <payloadRevision>1</payloadRevision>
        <timestamp>2017-07-27T15:17:58.000+02:00</timestamp>
    </event>
    <event>
        <aggregateIdentifier>NL.IMKAD.KadastraalObject.100</aggregateIdentifier>
        <sequenceNumber>3</sequenceNumber>
        <type>Perceel</type>
        <identifier>43f9cb65-d2e2-4573-811b-677c52d00296</identifier>
        <metaData>&lt;?xml version="1.0" encoding="UTF-8" standalone="yes"?&gt;&lt;metaData&gt;&lt;entries&gt;&lt;entry&gt;&lt;key&gt;registratie.version&lt;/key&gt;&lt;value xmlns:xsi="http://www.w3.org/2001/XMLSchema-instance" xmlns:xs="http://www.w3.org/2001/XMLSchema" xsi:type="xs:string"&gt;unspecified&lt;/value&gt;&lt;/entry&gt;&lt;entry&gt;&lt;key&gt;datatypes.version&lt;/key&gt;&lt;value xmlns:xsi="http://www.w3.org/2001/XMLSchema-instance" xmlns:xs="http://www.w3.org/2001/XMLSchema" xsi:type="xs:string"&gt;1.0.184&lt;/value&gt;&lt;/entry&gt;&lt;entry&gt;&lt;key&gt;event.version&lt;/key&gt;&lt;value xmlns:xsi="http://www.w3.org/2001/XMLSchema-instance" xmlns:xs="http://www.w3.org/2001/XMLSchema" xsi:type="xs:string"&gt;1.0.85&lt;/value&gt;&lt;/entry&gt;&lt;entry&gt;&lt;key&gt;axon.version&lt;/key&gt;&lt;value xmlns:xsi="http://www.w3.org/2001/XMLSchema-instance" xmlns:xs="http://www.w3.org/2001/XMLSchema" xsi:type="xs:string"&gt;4.5.9&lt;/value&gt;&lt;/entry&gt;&lt;/entries&gt;&lt;/metaData&gt;</metaData>
        <payload>&lt;?xml version="1.0" encoding="UTF-8" standalone="yes"?&gt;&lt;ns2:beperktRechtGevestigd xmlns:ns2="http://www.kadaster.nl/koers/registratie/event/kadastraalobject/rechtsfeit"&gt;&lt;eventIdentificatie&gt;&lt;aggregateId&gt;NL.IMKAD.KadastraalObject.100&lt;/aggregateId&gt;&lt;logischTijdstip&gt;2017-07-27T12:17:58.000+02:00&lt;/logischTijdstip&gt;&lt;onderhandenStuk&gt;NL.IMKAD.TIAStuk.157&lt;/onderhandenStuk&gt;&lt;onderhandenStukdeel&gt;NL.IMKAD.Stukdeel.158&lt;/onderhandenStukdeel&gt;&lt;formeelStuk&gt;NL.IMKAD.TIAStuk.157&lt;/formeelStuk&gt;&lt;formeelStukdeel&gt;NL.IMKAD.Stukdeel.158&lt;/formeelStukdeel&gt;&lt;/eventIdentificatie&gt;&lt;identificatie&gt;NL.IMKAD.ZakelijkRecht.1002&lt;/identificatie&gt;&lt;aard&gt;&lt;code&gt;14&lt;/code&gt;&lt;waarde&gt;Opstalrecht Nutsvoorzieningen&lt;/waarde&gt;&lt;/aard&gt;&lt;gestapeldOp&gt;NL.IMKAD.ZakelijkRecht.1001&lt;/gestapeldOp&gt;&lt;/ns2:beperktRechtGevestigd&gt;</payload>
        <payloadType>nl.kadaster.koers.event.kadastraalobject.rechtsfeit.BeperktRechtGevestigd</payloadType>
        <payloadRevision>1</payloadRevision>
        <timestamp>2017-07-27T15:17:58.000+02:00</timestamp>
    </event>
    <event>
        <aggregateIdentifier>NL.IMKAD.KadastraalObject.100</aggregateIdentifier>
        <sequenceNumber>4</sequenceNumber>
        <type>Perceel</type>
        <identifier>8a94bafd-f3fd-4f6c-8c89-a5c66c3a25ff</identifier>
        <metaData>&lt;?xml version="1.0" encoding="UTF-8" standalone="yes"?&gt;&lt;metaData&gt;&lt;entries&gt;&lt;entry&gt;&lt;key&gt;registratie.version&lt;/key&gt;&lt;value xmlns:xsi="http://www.w3.org/2001/XMLSchema-instance" xmlns:xs="http://www.w3.org/2001/XMLSchema" xsi:type="xs:string"&gt;unspecified&lt;/value&gt;&lt;/entry&gt;&lt;entry&gt;&lt;key&gt;datatypes.version&lt;/key&gt;&lt;value xmlns:xsi="http://www.w3.org/2001/XMLSchema-instance" xmlns:xs="http://www.w3.org/2001/XMLSchema" xsi:type="xs:string"&gt;1.0.184&lt;/value&gt;&lt;/entry&gt;&lt;entry&gt;&lt;key&gt;event.version&lt;/key&gt;&lt;value xmlns:xsi="http://www.w3.org/2001/XMLSchema-instance" xmlns:xs="http://www.w3.org/2001/XMLSchema" xsi:type="xs:string"&gt;1.0.85&lt;/value&gt;&lt;/entry&gt;&lt;entry&gt;&lt;key&gt;axon.version&lt;/key&gt;&lt;value xmlns:xsi="http://www.w3.org/2001/XMLSchema-instance" xmlns:xs="http://www.w3.org/2001/XMLSchema" xsi:type="xs:string"&gt;4.5.9&lt;/value&gt;&lt;/entry&gt;&lt;/entries&gt;&lt;/metaData&gt;</metaData>
        <payload>&lt;?xml version="1.0" encoding="UTF-8" standalone="yes"?&gt;&lt;ns2:zakelijkRechtTenaamgesteld xmlns:ns2="http://www.kadaster.nl/koers/registratie/event/kadastraalobject/rechtsfeit"&gt;&lt;eventIdentificatie&gt;&lt;aggregateId&gt;NL.IMKAD.KadastraalObject.100&lt;/aggregateId&gt;&lt;logischTijdstip&gt;2017-07-27T12:17:58.000+02:00&lt;/logischTijdstip&gt;&lt;onderhandenStuk&gt;NL.IMKAD.TIAStuk.157&lt;/onderhandenStuk&gt;&lt;onderhandenStukdeel&gt;NL.IMKAD.Stukdeel.158&lt;/onderhandenStukdeel&gt;&lt;formeelStuk&gt;NL.IMKAD.TIAStuk.157&lt;/formeelStuk&gt;&lt;formeelStukdeel&gt;NL.IMKAD.Stukdeel.158&lt;/formeelStukdeel&gt;&lt;/eventIdentificatie&gt;&lt;van&gt;NL.IMKAD.ZakelijkRecht.1002&lt;/van&gt;&lt;verkregenAandelen&gt;&lt;aandeel&gt;&lt;aandeelId&gt;NL.IMKAD.Aandeel.1002&lt;/aandeelId&gt;&lt;aandeel&gt;&lt;teller&gt;1&lt;/teller&gt;&lt;noemer&gt;1&lt;/noemer&gt;&lt;/aandeel&gt;&lt;geldtVoor&gt;&lt;tenaamstelling&gt;&lt;tenaamstellingId&gt;NL.IMKAD.Tenaamstelling.1002&lt;/tenaamstellingId&gt;&lt;tenNameVan&gt;NL.IMKAD.Persoon.2&lt;/tenNameVan&gt;&lt;/tenaamstelling&gt;&lt;/geldtVoor&gt;&lt;/aandeel&gt;&lt;/verkregenAandelen&gt;&lt;/ns2:zakelijkRechtTenaamgesteld&gt;</payload>
        <payloadType>nl.kadaster.koers.event.kadastraalobject.rechtsfeit.ZakelijkRechtTenaamgesteld</payloadType>
        <payloadRevision>1</payloadRevision>
        <timestamp>2017-07-27T15:17:58.000+02:00</timestamp>
    </event>
    <event>
        <aggregateIdentifier>NL.IMKAD.TIAStuk.157</aggregateIdentifier>
        <sequenceNumber>2</sequenceNumber>
        <type>TIAStuk</type>
        <identifier>2acac207-5ddf-4b67-bc74-eac728a2782b</identifier>
        <metaData>&lt;?xml version="1.0" encoding="UTF-8" standalone="yes"?&gt;&lt;metaData&gt;&lt;entries&gt;&lt;entry&gt;&lt;key&gt;registratie.version&lt;/key&gt;&lt;value xmlns:xsi="http://www.w3.org/2001/XMLSchema-instance" xmlns:xs="http://www.w3.org/2001/XMLSchema" xsi:type="xs:string"&gt;unspecified&lt;/value&gt;&lt;/entry&gt;&lt;entry&gt;&lt;key&gt;datatypes.version&lt;/key&gt;&lt;value xmlns:xsi="http://www.w3.org/2001/XMLSchema-instance" xmlns:xs="http://www.w3.org/2001/XMLSchema" xsi:type="xs:string"&gt;1.0.184&lt;/value&gt;&lt;/entry&gt;&lt;entry&gt;&lt;key&gt;event.version&lt;/key&gt;&lt;value xmlns:xsi="http://www.w3.org/2001/XMLSchema-instance" xmlns:xs="http://www.w3.org/2001/XMLSchema" xsi:type="xs:string"&gt;1.0.85&lt;/value&gt;&lt;/entry&gt;&lt;entry&gt;&lt;key&gt;axon.version&lt;/key&gt;&lt;value xmlns:xsi="http://www.w3.org/2001/XMLSchema-instance" xmlns:xs="http://www.w3.org/2001/XMLSchema" xsi:type="xs:string"&gt;4.5.9&lt;/value&gt;&lt;/entry&gt;&lt;/entries&gt;&lt;/metaData&gt;</metaData>
        <payload>&lt;?xml version="1.0" encoding="UTF-8" standalone="yes"?&gt;&lt;ns2:stukTransactieAfgerond xmlns:ns2="http://www.kadaster.nl/koers/registratie/event/stuk/technisch"&gt;&lt;eventIdentificatie&gt;&lt;aggregateId&gt;NL.IMKAD.TIAStuk.157&lt;/aggregateId&gt;&lt;logischTijdstip&gt;2017-07-27T12:17:58.000+02:00&lt;/logischTijdstip&gt;&lt;onderhandenStuk&gt;NL.IMKAD.TIAStuk.157&lt;/onderhandenStuk&gt;&lt;/eventIdentificatie&gt;&lt;verwerkingsResultaat&gt;VOLLEDIG_VERWERKT_STUK&lt;/verwerkingsResultaat&gt;&lt;stukUitgesloten&gt;false&lt;/stukUitgesloten&gt;&lt;kadastraalObjectIdentificaties&gt;&lt;kadastraalObjectIdentificatie&gt;&lt;uuid&gt;Apeldoorn-H02404&lt;/uuid&gt;&lt;kadastraleAanduiding&gt;&lt;kadastraleGemeente&gt;&lt;code&gt;50&lt;/code&gt;&lt;waarde&gt;Apeldoorn&lt;/waarde&gt;&lt;/kadastraleGemeente&gt;&lt;sectie&gt;H&lt;/sectie&gt;&lt;perceelNummer&gt;2404&lt;/perceelNummer&gt;&lt;/kadastraleAanduiding&gt;&lt;kadastraalObjectId&gt;NL.IMKAD.KadastraalObject.100&lt;/kadastraalObjectId&gt;&lt;/kadastraalObjectIdentificatie&gt;&lt;/kadastraalObjectIdentificaties&gt;&lt;/ns2:stukTransactieAfgerond&gt;</payload>
        <payloadType>nl.kadaster.koers.event.stuk.technisch.StukTransactieAfgerond</payloadType>
        <payloadRevision>2</payloadRevision>
        <timestamp>2017-07-27T15:17:58.000+02:00</timestamp>
    </event>
</events>
